{
  "store_name": "ครัวบ้านสวน",
  "source_url": "https://maps.google.com/?cid=demo",
  "reviews": [
    {"text": "อาหารอร่อยมาก รสชาติกลมกล่อม วัตถุดิบสดใหม่ ราคาคุ้มค่าสุดๆ จะกลับมาอีกแน่นอน", "rating": 5, "review_date": "2026-05-20"},
    {"text": "บริการดีมาก พนักงานยิ้มแย้มใส่ใจลูกค้า เสิร์ฟเร็วทันใจ ประทับใจสุดๆ", "rating": 5, "review_date": "2026-05-19"},
    {"text": "บรรยากาศร้านน่านั่ง ตกแต่งสวย แอร์เย็นสบาย เหมาะมานั่งชิลกับเพื่อน", "rating": 5, "review_date": "2026-05-18"},
    {"text": "รสชาติอาหารโอเค แต่บริการช้ามาก รอนานเกือบครึ่งชั่วโมงกว่าอาหารจะมา", "rating": 3, "review_date": "2026-05-17"},
    {"text": "อาหารจืดไปนิด แต่ปริมาณเยอะคุ้มราคา โดยรวมพอใช้ได้", "rating": 3, "review_date": "2026-05-16"},
    {"text": "พนักงานหยาบคายมาก พูดจาไม่ดี ไม่ประทับใจเลย ไม่แนะนำ", "rating": 1, "review_date": "2026-05-15"},
    {"text": "ร้านสกปรก ห้องน้ำโทรม โต๊ะเหนียวเหนอะหนะ บรรยากาศแย่มาก", "rating": 1, "review_date": "2026-05-14"},
    {"text": "เมนูเด็ดคือต้มยำกุ้ง รสชาติเข้มข้น หอมเครื่อง อร่อยจริง แนะนำเลย", "rating": 5, "review_date": "2026-05-13"},
    {"text": "อาหารแพงไปหน่อยเมื่อเทียบกับปริมาณ รสชาติก็งั้นๆ ไม่ค่อยประทับใจ", "rating": 2, "review_date": "2026-05-12"},
    {"text": "ร้านอยู่ติดถนนใหญ่ หาง่าย มีที่จอดรถ", "rating": 3, "review_date": "2026-05-11"},
    {"text": "บริการรวดเร็ว พนักงานน่ารัก คอยเติมน้ำให้ตลอด ใส่ใจดีมาก", "rating": 5, "review_date": "2026-05-10"},
    {"text": "อาหารอร่อย แต่ร้านเสียงดังมาก คุยกันแทบไม่ได้ยิน บรรยากาศวุ่นวาย", "rating": 3, "review_date": "2026-05-09"},
    {"text": "วัตถุดิบไม่สด กุ้งมีกลิ่น กินแล้วไม่สบายท้อง ผิดหวังมาก", "rating": 1, "review_date": "2026-05-08"},
    {"text": "ตกแต่งร้านสวยมาก มุมถ่ายรูปเยอะ แสงสวย เหมาะถ่ายรูปลงโซเชียล", "rating": 5, "review_date": "2026-05-07"},
    {"text": "รอคิวนานมาก พนักงานไม่ค่อยสนใจลูกค้า เรียกหลายรอบกว่าจะมา", "rating": 2, "review_date": "2026-05-06"},
    {"text": "อาหารรสชาติดี ของหวานอร่อยมาก โดยเฉพาะบัวลอย หอมกะทิ", "rating": 5, "review_date": "2026-05-05"},
    {"text": "ราคาปกติ อาหารพอกินได้ ไม่มีอะไรโดดเด่นเป็นพิเศษ", "rating": 3, "review_date": "2026-05-04"},
    {"text": "แอร์ไม่เย็น ร้อนมาก นั่งแล้วอึดอัด อยากให้ปรับปรุงเรื่องนี้", "rating": 2, "review_date": "2026-05-03"},
    {"text": "พนักงานบริการดีเยี่ยม แนะนำเมนูเก่ง ใส่ใจรายละเอียด ประทับใจ", "rating": 5, "review_date": "2026-05-02"},
    {"text": "อาหารเค็มไปมาก ทานไม่ค่อยไหว บอกพนักงานแล้วก็ยังเหมือนเดิม", "rating": 2, "review_date": "2026-05-01"},
    {"text": "บรรยากาศดี นั่งสบาย เพลงเพราะ เหมาะมาทานมื้อค่ำกับครอบครัว", "rating": 4, "review_date": "2026-04-30"},
    {"text": "เมนูอาหารหลากหลาย รสชาติใช้ได้ บริการก็โอเค ราคาไม่แพง", "rating": 4, "review_date": "2026-04-29"},
    {"text": "ผิดหวังมาก สั่งอาหารผิด รอนาน พอทักท้วงพนักงานก็ทำหน้าไม่พอใจ", "rating": 1, "review_date": "2026-04-28"},
    {"text": "อร่อยทุกจาน วัตถุดิบสด พนักงานบริการดี บรรยากาศก็น่านั่ง คุ้มค่ามาก", "rating": 5, "review_date": "2026-04-27"},
    {"text": "ร้านกว้างขวาง สะอาด มีโซนนั่งหลายแบบ ที่จอดรถสะดวก", "rating": 4, "review_date": "2026-04-26"},
    {"text": "อาหารมาช้ามาก แถมเสิร์ฟไม่ครบ ต้องทวงหลายรอบ บริการต้องปรับปรุง", "rating": 2, "review_date": "2026-04-25"},
    {"text": "รสชาติกลางๆ ไม่ได้แย่แต่ก็ไม่ได้เด่น ราคาพอรับได้", "rating": 3, "review_date": "2026-04-24"},
    {"text": "ชอบมากร้านนี้ อาหารอร่อย พนักงานเป็นกันเอง บรรยากาศอบอุ่น", "rating": 5, "review_date": "2026-04-23"},
    {"text": "เครื่องดื่มหวานเกินไป แต่อาหารคาวอร่อยดี โดยรวมโอเค", "rating": 3, "review_date": "2026-04-22"},
    {"text": "พนักงานน้อย บริการไม่ทัน รอนานมากในช่วงพีค ควรเพิ่มคน", "rating": 2, "review_date": "2026-04-21"}
  ]
}
